nacos/auto/__init__.py
nacos/auto/constants.py
nacos/auto/config/__init__.py
nacos/auto/config/loader.py
nacos/auto/config/validator.py
nacos/auto/detectors/__init__.py
nacos/auto/detectors/framework_detector.py
nacos/auto/detectors/service_detector.py
nacos/auto/discovery/__init__.py
nacos/auto/discovery/aiohttp_ext.py
nacos/auto/discovery/core.py
nacos/auto/discovery/error_handlers.py
nacos/auto/discovery/httpx_ext.py
nacos/auto/discovery/nacos_discovery.py
nacos/auto/discovery/requests_ext.py
nacos/auto/discovery/url_resolver.py
nacos/auto/discovery/urllib_ext.py
nacos/auto/discovery/utils.py
nacos/auto/discovery/ext/__init__.py
nacos/auto/discovery/ext/aiohttp.py
nacos/auto/discovery/ext/httpx.py
nacos/auto/discovery/ext/manager.py
nacos/auto/discovery/ext/requests.py
nacos/auto/discovery/ext/urllib.py
nacos/auto/injectors/__init__.py
nacos/auto/injectors/import_hook.py
nacos/auto/injectors/injector.py
nacos/auto/middleware/__init__.py
nacos/auto/middleware/asgi.py
nacos/auto/middleware/wsgi.py
nacos/auto/registration/__init__.py
nacos/auto/registration/__main__.py
nacos/auto/registration/enabled/__init__.py
nacos/auto/services/__init__.py
nacos/auto/services/manager.py
nacos/auto/services/registry.py
nacos/auto/services/shutdown.py
nacos/utils/__init__.py
nacos/utils/tools.py
nacos_serving_python-0.1.3.dist-info/METADATA
nacos_serving_python-0.1.3.dist-info/WHEEL
nacos_serving_python-0.1.3.dist-info/entry_points.txt
nacos_serving_python-0.1.3.dist-info/licenses/LICENSE
nacos_serving_python-0.1.3.dist-info/RECORD
