Metadata-Version: 2.4
Name: nacos-serving-python
Version: 0.1.3
Summary: Nacos 2.x async serving & config SDK with auto registration and discovery extensions
License-File: LICENSE
Requires-Python: >=3.12
Requires-Dist: aiohttp>=3.10.11
Requires-Dist: httpx>=0.28.0
Requires-Dist: nacos-sdk-python>=2.0.5
Requires-Dist: psutil>=5.8.0
Requires-Dist: pyyaml>=5.1
Requires-Dist: watchdog>=2.0.0
Provides-Extra: dev
Requires-Dist: pyright>=1.1.389; extra == 'dev'
